README.md
README.rst
setup.py
WebProcessor.egg-info/PKG-INFO
WebProcessor.egg-info/SOURCES.txt
WebProcessor.egg-info/dependency_links.txt
WebProcessor.egg-info/requires.txt
WebProcessor.egg-info/top_level.txt
driver/Requirements/GetRequirements.py
driver/Requirements/__init.py
driver/Requirements/download_base_requirements.py
driver/WebProcessor/WebFilter.py
driver/WebProcessor/WebProcessor.py
driver/WebProcessor/__init.py
driver/Requirements/GetRequirements.py
driver/Requirements/__init.py
driver/Requirements/download_base_requirements.py
driver/WebProcessor/WebFilter.py
driver/WebProcessor/WebProcessor.py
driver/WebProcessor/__init.py