Metadata-Version: 1.1
Name: WebProcessor
Version: 0.1.8
Summary: A package for loading websites and extracting information: THIS IS FOR EDUCATIONAL PURPOSES ONLY OR IF YOU HAVE CONSENT TO USE THAT SITES INFO!
Home-page: https://github.com/TheBlockNinja/WebProcessor
Author: Seann Moser
Author-email: seannsea@gmail.com
License: UNKNOWN
Platform: UNKNOWN
Classifier: Programming Language :: Python :: 3.5
